autocrop_kh/__init__.py
autocrop_kh-0.0.3.dist-info/LICENSE
autocrop_kh-0.0.3.dist-info/METADATA
autocrop_kh-0.0.3.dist-info/WHEEL
autocrop_kh-0.0.3.dist-info/top_level.txt
autocrop_kh-0.0.3.dist-info/RECORD
