Metadata-Version: 2.1
Name: autocrop-kh
Version: 0.0.3
Summary: Document Extraction Inference API using DeepLabV3 with Pretrain Model
Home-page: https://github.com/MetythornPenn/autocrop_kh.git
Author: Metythorn Penn
Author-email: metythorn@gmail.com
License: Apache Software License 2.0
Keywords: autocrop_kh
Platform: UNKNOWN
Classifier: Natural Language :: English
Classifier: License :: OSI Approved :: Apache Software License
Classifier: Operating System :: OS Independent
Classifier: Programming Language :: Python :: 3
Requires-Dist: torch
Requires-Dist: torchvision
Requires-Dist: numpy
Requires-Dist: opencv-python-headless
Requires-Dist: onnx
